client/__init__.py
client/android_element.py
client/uia_client.py
common/__init__.py
common/http_client.py
common/logger.py
common/models.py
common/resp_handler.py
common/sonic_exception.py
uia2/__init__.py
uia2/driver.py
sonic_uia2_client-0.0.9.dist-info/LICENSE
sonic_uia2_client-0.0.9.dist-info/METADATA
sonic_uia2_client-0.0.9.dist-info/WHEEL
sonic_uia2_client-0.0.9.dist-info/top_level.txt
sonic_uia2_client-0.0.9.dist-info/RECORD
