Metadata-Version: 2.1
Name: sonic-uia2-client
Version: 0.0.9
Home-page: https://github.com/SonicCloudOrg/sonic-uiautomator2-python-client
Author: SonicCloudOrg
Author-email: soniccloudorg@163.com
License: MIT
Classifier: Natural Language :: English
Classifier: Operating System :: OS Independent
Classifier: Programming Language :: Python
Classifier: Programming Language :: Python :: 3
Classifier: Topic :: Software Development :: Libraries :: Python Modules
Classifier: Topic :: Software Development :: Testing
Requires-Python: >=3
License-File: LICENSE
